live_template/__init__.py
live_template/adapters/__init__.py
live_template/adapters/lt_aiogram/__init__.py
live_template/adapters/lt_aiogram/parser.py
live_template/adapters/lt_aiogram/router.py
live_template/adapters/lt_aiogram/utils.py
live_template/core/__init__.py
live_template/core/core.py
live_template/core/router/base_router.py
live_template/core/storage/parser.py
live_template/core/storage/storage.py
live_template/core/templates/always_retry_false.py
live_template/core/templates/always_retry_true.py
live_template/core/templates/examples/default_template_with_adjusted_buttons.py
live_template/core/templates/examples/default_template_with_full_mapped_buttons.py
live_template/core/templates/list_templates.py
live_template/core/templates/live_template_start.py
live_template/core/templates/no_templates.py
live_template/core/templates/retry_btn.py
live_template/core/utils/utils.py
live_template/core/watcher/watcher.py
live_template-0.1.5.dist-info/LICENSE
live_template-0.1.5.dist-info/METADATA
live_template-0.1.5.dist-info/WHEEL
live_template-0.1.5.dist-info/RECORD
