Metadata-Version: 2.3
Name: live_template
Version: 0.1.5
Summary: LiveTemplate is a tool for local development and testing of Telegram bots, designed to simplify working with message templates and instantly display changes without restarting the bot.
License: MIT
Author: gPlorovg
Author-email: gplorovg@gmail.com
Requires-Python: >=3.10
Classifier: License :: OSI Approved :: MIT License
Classifier: Programming Language :: Python :: 3
Classifier: Programming Language :: Python :: 3.10
Classifier: Programming Language :: Python :: 3.11
Classifier: Programming Language :: Python :: 3.12
Classifier: Programming Language :: Python :: 3.13
Provides-Extra: aiogram
Provides-Extra: ptb
Requires-Dist: aiogram (>=3.10,<4.0) ; extra == "aiogram"
Requires-Dist: python-telegram-bot (>=21.0,<22.0) ; extra == "ptb"
Requires-Dist: watchdog (>=6.0.0,<7.0.0)
